{
    "plist": [
        {
            "img": "txt:张枣",
            "url": "http://www.shigeku.com/shiku/xs/zhangzao.htm",
            "txt": "张枣"
        },
        {
            "img": "txt:清平",
            "url": "http://www.shigeku.com/shiku/xs/qingping.htm",
            "txt": "清平"
        },
        {
            "img": "txt:唐亚平",
            "url": "http://www.shigeku.com/shiku/xs/tangyaping.htm",
            "txt": "唐亚平"
        },
        {
            "img": "txt:王寅",
            "url": "http://www.shigeku.com/shiku/xs/wangyin.htm",
            "txt": "王寅"
        },
        {
            "img": "txt:凸凹",
            "url": "http://www.shigeku.com/shiku/xs/tuao.htm",
            "txt": "凸凹"
        },
        {
            "img": "txt:紫薇",
            "url": "http://www.shigeku.com/shiku/xs/ziwei.htm",
            "txt": "紫薇"
        },
        {
            "img": "txt:谭延桐",
            "url": "http://www.shigeku.com/shiku/xs/tanyantong.htm",
            "txt": "谭延桐"
        },
        {
            "img": "txt:林耀德",
            "url": "http://www.shigeku.com/shiku/xs/linyaode.htm",
            "txt": "林耀德"
        },
        {
            "img": "txt:胡刚毅",
            "url": "http://www.shigeku.com/shiku/xs/hugangyi.htm",
            "txt": "胡刚毅"
        },
        {
            "img": "txt:陈云虎",
            "url": "http://www.shigeku.com/shiku/xs/chenyunhu.htm",
            "txt": "陈云虎"
        },
        {
            "img": "txt:萧沉",
            "url": "http://www.shigeku.com/shiku/xs/xiaochen.htm",
            "txt": "萧沉"
        },
        {
            "img": "txt:指纹",
            "url": "http://www.shigeku.com/shiku/xs/zhiwen.htm",
            "txt": "指纹"
        },
        {
            "img": "txt:麦城",
            "url": "http://www.shigeku.com/shiku/xs/maicheng.htm",
            "txt": "麦城"
        },
        {
            "img": "txt:万夏",
            "url": "http://www.shigeku.com/shiku/xs/wanxia.htm",
            "txt": "万夏"
        },
        {
            "img": "txt:马松",
            "url": "http://www.shigeku.com/shiku/xs/masong.htm",
            "txt": "马松"
        },
        {
            "img": "txt:周泽雄",
            "url": "http://www.shigeku.com/shiku/xs/zhouzexiong.htm",
            "txt": "周泽雄"
        },
        {
            "img": "txt:张远山",
            "url": "http://www.shigeku.com/shiku/xs/zhangyuanshan.htm",
            "txt": "张远山"
        },
        {
            "img": "txt:车前子",
            "url": "http://www.shigeku.com/shiku/xs/cheqianzi.htm",
            "txt": "车前子"
        },
        {
            "img": "txt:李亚伟",
            "url": "http://www.shigeku.com/shiku/xs/liyawei.htm",
            "txt": "李亚伟"
        },
        {
            "img": "txt:何小竹",
            "url": "http://www.shigeku.com/shiku/xs/hexiaozhu.htm",
            "txt": "何小竹"
        },
        {
            "img": "txt:宋渠宋炜",
            "url": "http://www.shigeku.com/shiku/xs/songqu.htm",
            "txt": "宋渠宋炜"
        },
        {
            "img": "txt:西川",
            "url": "http://www.shigeku.com/shiku/xs/xichuan.htm",
            "txt": "西川"
        },
        {
            "img": "txt:郑单衣",
            "url": "http://www.shigeku.com/shiku/xs/zhengdanyi.htm",
            "txt": "郑单衣"
        },
        {
            "img": "txt:李德武",
            "url": "http://www.shigeku.com/shiku/xs/lidewu.htm",
            "txt": "李德武"
        },
        {
            "img": "txt:吉木狼格",
            "url": "http://www.shigeku.com/shiku/xs/jimulangge.htm",
            "txt": "吉木狼格"
        },
        {
            "img": "txt:黄灿然",
            "url": "http://www.shigeku.com/shiku/xs/huangcanran.htm",
            "txt": "黄灿然"
        },
        {
            "img": "txt:远村",
            "url": "http://www.shigeku.com/shiku/xs/yuancun.htm",
            "txt": "远村"
        },
        {
            "img": "txt:飞沙",
            "url": "http://www.shigeku.com/shiku/xs/feisha.htm",
            "txt": "飞沙"
        },
        {
            "img": "txt:席君秋",
            "url": "http://www.shigeku.com/shiku/xs/xijunqiu.htm",
            "txt": "席君秋"
        },
        {
            "img": "txt:郭志杰",
            "url": "http://www.shigeku.com/shiku/xs/guozhijie.htm",
            "txt": "郭志杰"
        },
        {
            "img": "txt:渭波",
            "url": "http://www.shigeku.com/shiku/xs/weibo.htm",
            "txt": "渭波"
        },
        {
            "img": "txt:林童",
            "url": "http://www.shigeku.com/shiku/xs/lintong.htm",
            "txt": "林童"
        },
        {
            "img": "txt:陈惠芳",
            "url": "http://www.shigeku.com/shiku/xs/chenhuifang.htm",
            "txt": "陈惠芳"
        },
        {
            "img": "txt:黄梵",
            "url": "http://www.shigeku.com/shiku/xs/huangfan.htm",
            "txt": "黄梵"
        },
        {
            "img": "txt:中岛",
            "url": "http://www.shigeku.com/shiku/xs/zhongdao.htm",
            "txt": "中岛"
        },
        {
            "img": "txt:梁晓明",
            "url": "http://www.shigeku.com/shiku/xs/liangxiaoming.htm",
            "txt": "梁晓明"
        },
        {
            "img": "txt:张敏华",
            "url": "http://www.shigeku.com/shiku/xs/zhangminhua.htm",
            "txt": "张敏华"
        },
        {
            "img": "txt:海子",
            "url": "http://www.shigeku.com/shiku/xs/haizi.htm",
            "txt": "海子"
        },
        {
            "img": "txt:颜溶",
            "url": "http://www.shigeku.com/shiku/xs/yanrong.htm",
            "txt": "颜溶"
        },
        {
            "img": "txt:刘伟雄",
            "url": "http://www.shigeku.com/shiku/xs/liuweixiong.htm",
            "txt": "刘伟雄"
        },
        {
            "img": "txt:默默",
            "url": "http://www.shigeku.com/shiku/xs/momo.htm",
            "txt": "默默"
        },
        {
            "img": "txt:小安",
            "url": "http://www.shigeku.com/shiku/xs/xiaoan.htm",
            "txt": "小安"
        },
        {
            "img": "txt:徐东明",
            "url": "http://www.shigeku.com/shiku/xs/xudongming.htm",
            "txt": "徐东明"
        },
        {
            "img": "txt:刘漫流",
            "url": "http://www.shigeku.com/shiku/xs/liumanliu.htm",
            "txt": "刘漫流"
        },
        {
            "img": "txt:恒平",
            "url": "http://www.shigeku.com/shiku/xs/hengping.htm",
            "txt": "恒平"
        },
        {
            "img": "txt:瓦兰",
            "url": "http://www.shigeku.com/shiku/xs/walan.htm",
            "txt": "瓦兰"
        },
        {
            "img": "txt:小海",
            "url": "http://www.shigeku.com/shiku/xs/xiaohai.htm",
            "txt": "小海"
        },
        {
            "img": "txt:尚仲敏",
            "url": "http://www.shigeku.com/shiku/xs/shangzhongmin.htm",
            "txt": "尚仲敏"
        },
        {
            "img": "txt:王琪博",
            "url": "http://www.shigeku.com/shiku/xs/wangqibo.htm",
            "txt": "王琪博"
        },
        {
            "img": "txt:燕晓东",
            "url": "http://www.shigeku.com/shiku/xs/yanxiaodong.htm",
            "txt": "燕晓东"
        },
        {
            "img": "txt:雁西",
            "url": "http://www.shigeku.com/shiku/xs/yanxi.htm",
            "txt": "雁西"
        },
        {
            "img": "txt:谢宜兴",
            "url": "http://www.shigeku.com/shiku/xs/xieyixing.htm",
            "txt": "谢宜兴"
        },
        {
            "img": "txt:卢卫平",
            "url": "http://www.shigeku.com/shiku/xs/luweiping.htm",
            "txt": "卢卫平"
        },
        {
            "img": "txt:禄琴",
            "url": "http://www.shigeku.com/shiku/xs/luqin.htm",
            "txt": "禄琴"
        },
        {
            "img": "txt:汪峰",
            "url": "http://www.shigeku.com/shiku/xs/wangfeng.htm",
            "txt": "汪峰"
        },
        {
            "img": "txt:韩高琦",
            "url": "http://www.shigeku.com/shiku/xs/hangaoqi.htm",
            "txt": "韩高琦"
        },
        {
            "img": "txt:宫哲",
            "url": "http://www.shigeku.com/shiku/xs/gongzhe.htm",
            "txt": "宫哲"
        },
        {
            "img": "txt:李青松",
            "url": "http://www.shigeku.com/shiku/xs/liqingsong.htm",
            "txt": "李青松"
        },
        {
            "img": "txt:京不特",
            "url": "http://www.shigeku.com/shiku/xs/jingbute.htm",
            "txt": "京不特"
        },
        {
            "img": "txt:蒋蓝",
            "url": "http://www.shigeku.com/shiku/xs/jianglan.htm",
            "txt": "蒋蓝"
        },
        {
            "img": "txt:刘立杆",
            "url": "http://www.shigeku.com/shiku/xs/liuligan.htm",
            "txt": "刘立杆"
        },
        {
            "img": "txt:李森",
            "url": "http://www.shigeku.com/shiku/xs/lisen.htm",
            "txt": "李森"
        },
        {
            "img": "txt:邱勇",
            "url": "http://www.shigeku.com/shiku/xs/qiuyong.htm",
            "txt": "邱勇"
        },
        {
            "img": "txt:吴新宇",
            "url": "http://www.shigeku.com/shiku/xs/wuxinyu.htm",
            "txt": "吴新宇"
        },
        {
            "img": "txt:庞清明",
            "url": "http://www.shigeku.com/shiku/xs/pangqingming.htm",
            "txt": "庞清明"
        },
        {
            "img": "txt:张志",
            "url": "http://www.shigeku.com/shiku/xs/zhangzhi.htm",
            "txt": "张志"
        },
        {
            "img": "txt:夜林",
            "url": "http://www.shigeku.com/shiku/xs/yelin.htm",
            "txt": "夜林"
        },
        {
            "img": "txt:周瓒",
            "url": "http://www.shigeku.com/shiku/xs/zhouzan.htm",
            "txt": "周瓒"
        },
        {
            "img": "txt:宋晓杰",
            "url": "http://www.shigeku.com/shiku/xs/songxiaojie.htm",
            "txt": "宋晓杰"
        },
        {
            "img": "txt:刘文旋",
            "url": "http://www.shigeku.com/shiku/xs/liuwenxuan.htm",
            "txt": "刘文旋"
        },
        {
            "img": "txt:阳阳",
            "url": "http://www.shigeku.com/shiku/xs/yangyang.htm",
            "txt": "阳阳"
        },
        {
            "img": "txt:刑天",
            "url": "http://www.shigeku.com/shiku/xs/xingtian.htm",
            "txt": "刑天"
        },
        {
            "img": "txt:李尚朝",
            "url": "http://www.shigeku.com/shiku/xs/lishangchao.htm",
            "txt": "李尚朝"
        },
        {
            "img": "txt:叶匡政",
            "url": "http://www.shigeku.com/shiku/xs/yekuangzheng.htm",
            "txt": "叶匡政"
        },
        {
            "img": "txt:路也",
            "url": "http://www.shigeku.com/shiku/xs/luye.htm",
            "txt": "路也"
        },
        {
            "img": "txt:马莉",
            "url": "http://www.shigeku.com/shiku/xs/mali.htm",
            "txt": "马莉"
        },
        {
            "img": "txt:代薇",
            "url": "http://www.shigeku.com/shiku/xs/daiwei.htm",
            "txt": "代薇"
        },
        {
            "img": "txt:阿翔",
            "url": "http://www.shigeku.com/shiku/xs/axiang.htm",
            "txt": "阿翔"
        },
        {
            "img": "txt:徐柏坚",
            "url": "http://www.shigeku.com/shiku/xs/xubojian.htm",
            "txt": "徐柏坚"
        },
        {
            "img": "txt:唐朝晖",
            "url": "http://www.shigeku.com/shiku/xs/tangzhaohui.htm",
            "txt": "唐朝晖"
        },
        {
            "img": "txt:海啸",
            "url": "http://www.shigeku.com/shiku/xs/haixiao.htm",
            "txt": "海啸"
        },
        {
            "img": "txt:柯平",
            "url": "http://www.shigeku.com/shiku/xs/keping.htm",
            "txt": "柯平"
        },
        {
            "img": "txt:洛湃",
            "url": "http://www.shigeku.com/shiku/xs/luopai.htm",
            "txt": "洛湃"
        },
        {
            "img": "txt:南野",
            "url": "http://www.shigeku.com/shiku/xs/nanye.htm",
            "txt": "南野"
        },
        {
            "img": "txt:沈奇",
            "url": "http://www.shigeku.com/shiku/xs/shenqi.htm",
            "txt": "沈奇"
        },
        {
            "img": "txt:沈睿",
            "url": "http://www.shigeku.com/shiku/xs/shenrui.htm",
            "txt": "沈睿"
        },
        {
            "img": "txt:宋琳",
            "url": "http://www.shigeku.com/shiku/xs/songlin.htm",
            "txt": "宋琳"
        },
        {
            "img": "txt:夏宇",
            "url": "http://www.shigeku.com/shiku/xs/xiayu.htm",
            "txt": "夏宇"
        },
        {
            "img": "txt:李轻松",
            "url": "http://www.shigeku.com/shiku/xs/liqingsong2.htm",
            "txt": "李轻松"
        },
        {
            "img": "txt:张真",
            "url": "http://www.shigeku.com/shiku/xs/zhangzhen.htm",
            "txt": "张真"
        },
        {
            "img": "txt:伊路",
            "url": "http://www.shigeku.com/shiku/xs/yilu.htm",
            "txt": "伊路"
        },
        {
            "img": "txt:邓诗鸿",
            "url": "http://www.shigeku.com/shiku/xs/dengshihong.htm",
            "txt": "邓诗鸿"
        },
        {
            "img": "txt:老刀",
            "url": "http://www.shigeku.com/shiku/xs/laodao.htm",
            "txt": "老刀"
        },
        {
            "img": "txt:雷默",
            "url": "http://www.shigeku.com/shiku/xs/leimo.htm",
            "txt": "雷默"
        },
        {
            "img": "txt:叶舟",
            "url": "http://www.shigeku.com/shiku/xs/yezhou.htm",
            "txt": "叶舟"
        }
    ]
}
